flask_packer/__init__.py
flask_packer/_base.py
flask_packer/_errors.py
flask_packer/_extension.py
flask_packer/tags/__init__.py
flask_packer/tags/css.py
flask_packer/tags/js.py
flask_packer-2.1.8.dist-info/LICENSE
flask_packer-2.1.8.dist-info/METADATA
flask_packer-2.1.8.dist-info/WHEEL
flask_packer-2.1.8.dist-info/top_level.txt
flask_packer-2.1.8.dist-info/RECORD
